sundew/__init__.py
sundew/__main__.py
sundew/adaptive_learning.py
sundew/automl_optimization.py
sundew/batch_processing.py
sundew/benchmarking.py
sundew/cli.py
sundew/config.py
sundew/config_presets.py
sundew/control_policies.py
sundew/core.py
sundew/demo.py
sundew/ecg.py
sundew/energy.py
sundew/energy_models.py
sundew/enhanced_core.py
sundew/gating.py
sundew/gating_strategies.py
sundew/humanitarian_health.py
sundew/information_theory.py
sundew/interfaces.py
sundew/monitoring.py
sundew/runtime.py
sundew/runtime_adapters.py
sundew/significance_models.py
sundew/simple_core.py
sundew/theoretical_analysis.py
sundew_algorithms-0.7.1.dist-info/licenses/LICENSE
sundew_algorithms-0.7.1.dist-info/METADATA
sundew_algorithms-0.7.1.dist-info/WHEEL
sundew_algorithms-0.7.1.dist-info/entry_points.txt
sundew_algorithms-0.7.1.dist-info/top_level.txt
sundew_algorithms-0.7.1.dist-info/RECORD
