Metadata-Version: 2.4
Name: sundew-algorithms
Version: 0.7.1
Summary: Sundew Algorithm — bio-inspired, energy-aware selective activation for edge AI systems.
Author-email: Oluwafemi Idiakhoa <oluwafemidiakhoa@gmail.com>
License: MIT License
Project-URL: Homepage, https://oluwafemidiakhoa.github.io
Project-URL: Repository, https://github.com/oluwafemidiakhoa/sundew_algorithms
Project-URL: Issues, https://github.com/oluwafemidiakhoa/sundew_algorithms/issues
Project-URL: Documentation, https://oluwafemidiakhoa.github.io
Project-URL: PyPI, https://pypi.org/project/sundew-algorithms/
Project-URL: DOI, https://doi.org/10.5281/zenodo.17118217
Project-URL: ORCID, https://orcid.org/0009-0008-7911-1171
Keywords: edge-ai,energy,gating,event-driven,ecg,computer-vision,adaptive-computation,selective-activation
Classifier: Development Status :: 4 - Beta
Classifier: Intended Audience :: Science/Research
Classifier: License :: OSI Approved :: MIT License
Classifier: Programming Language :: Python :: 3
Classifier: Programming Language :: Python :: 3 :: Only
Classifier: Programming Language :: Python :: 3.10
Classifier: Programming Language :: Python :: 3.11
Classifier: Programming Language :: Python :: 3.12
Classifier: Topic :: Scientific/Engineering :: Artificial Intelligence
Requires-Python: >=3.10
License-File: LICENSE
Requires-Dist: numpy>=1.22
Requires-Dist: pandas>=1.5.0
Provides-Extra: dev
Requires-Dist: ruff>=0.13.0; extra == "dev"
Requires-Dist: mypy>=1.7; extra == "dev"
Requires-Dist: pytest>=7; extra == "dev"
Requires-Dist: pytest-cov>=4; extra == "dev"
Requires-Dist: hypothesis>=6; extra == "dev"
Requires-Dist: build>=1.2.1; extra == "dev"
Requires-Dist: twine>=5.1.1; extra == "dev"
Requires-Dist: types-requests; extra == "dev"
Provides-Extra: viz
Requires-Dist: matplotlib<4.0,>=3.7; extra == "viz"
Provides-Extra: video
Requires-Dist: opencv-python>=4.8; extra == "video"
Dynamic: license-file
